HiPart/__init__.py
HiPart/__partition_class.py
HiPart/__utility_functions.py
HiPart/clustering.py
HiPart/interactive_visualization.py
HiPart/visualizations.py
HiPart/assets/int_viz.css
hipart-1.0.6.dist-info/LICENSE
hipart-1.0.6.dist-info/METADATA
hipart-1.0.6.dist-info/WHEEL
hipart-1.0.6.dist-info/top_level.txt
hipart-1.0.6.dist-info/RECORD
