Metadata-Version: 2.1
Name: HiPart
Version: 1.0.6
Summary: A hierarchical divisive clustering toolbox
Home-page: https://github.com/panagiotisanagnostou/HiPart
Author: Panagiotis Anagnostou
Author-email: panagno@uth.gr
License: MIT License
Project-URL: Documentation, https://hipart.readthedocs.io/en/latest/
Project-URL: Source Code, https://github.com/panagiotisanagnostou/HiPart/
Project-URL: Bug Tracker, https://github.com/panagiotisanagnostou/HiPart/issues
Keywords: data structure,tree,tools
Classifier: Development Status :: 5 - Production/Stable
Classifier: Environment :: Console
Classifier: Environment :: Web Environment
Classifier: Intended Audience :: Science/Research
Classifier: License :: OSI Approved :: MIT License
Classifier: Natural Language :: English
Classifier: Operating System :: OS Independent
Classifier: Programming Language :: Python
Classifier: Programming Language :: Python :: 3
Classifier: Programming Language :: Python :: 3.8
Classifier: Programming Language :: Python :: 3.9
Classifier: Programming Language :: Python :: 3.10
Classifier: Programming Language :: Python :: 3.11
Classifier: Programming Language :: Python :: 3.12
Classifier: Topic :: Documentation :: Sphinx
Classifier: Topic :: Internet :: WWW/HTTP :: Dynamic Content
Classifier: Topic :: Software Development :: Libraries :: Python Modules
Classifier: Topic :: Scientific/Engineering :: Artificial Intelligence
Requires-Python: >=3.7
License-File: LICENSE
Requires-Dist: numpy
Requires-Dist: treelib>=1.6
Requires-Dist: scipy<=1.15.3
Requires-Dist: scikit-learn
Requires-Dist: statsmodels>=0.13
Requires-Dist: kdepy
Requires-Dist: matplotlib
Requires-Dist: plotly
Requires-Dist: dash>=2.0
